{
    "redPine": {
        "treeName": "plot06_redpine",
        "Density": "plot06_redpine_density",
        "DBH": "plot06_redpine_DBH",
        "AverageLAI": "plot06_redpine_AverageLAI",
        "Height": "plot06_redpine_Height",
        "Age": "plot06_redpine_Age"
    },

    "oak": {
        "treeName": "plot06_oak",
        "Density": "plot06_oak_density",
        "DBH": "plot06_oak_DBH",
        "AverageLAI": "plot06_oak_AverageLAI",
        "Height": "plot06_oak_Height",
        "Age": "plot06_oak_Age"
    },

    "beech": {
        "treeName": "plot06_beech",
        "Density": "plot06_beech_Density",
        "DBH": "plot06_beech_DBH",
        "AverageLAI": "plot06_beech_AverageLAI",
        "Height": "plot06_beech_Height",
        "Age": "plot06_beech_Age"
    },

    "birch":{
        "treeName": "plot06_birch",
        "Density": "plot06_birch_Density",
        "DBH": "plot06_birch_DBH",
        "AverageLAI": "plot06_birch_AverageLAI",
        "Height": "plot06_birch_Height",
        "Age": "plot06_birch_Age"
    },

    "whitePine":{
        "treeName": "plot06_whitepine",
        "Density": "plot06_whitepine_Density",
        "DBH": "plot06_whitepine_DBH",
        "AverageLAI": "plot06_whitepine_AverageLAI",
        "Height": "plot06_whitepine_Height",
        "Age": "plot06_whitepine_Age"
    },

    "redMaple": {
        "treeName": "plot06_redmaple",
        "Density": "plot06_redmaple_Density",
        "DBH": "plot06_redmaple_DBH",
        "AverageLAI": "plot06_redmaple_AverageLAI",
        "Height": "plot06_redmaple_Height",
        "Age": "plot06_redmaple_Age"
    },

    "redOak": {
        "treeName": "plot06_redoak",
        "Density": "plot06_redoak_Density",
        "DBH": "plot06_redoak_DBH",
        "AverageLAI": "plot06_redoak_AverageLAI",
        "Height": "plot06_redoak_Height",
        "Age": "plot06_redoak_Age"
    },

    "envData": {
        "Humility": "plot06_Humidity",
        "Temp": "plot06_Temp",
        "CO2CONCEN": "plot06_CO2",
        "O2CONCEN": "plot06_O2",
        "SoilPH": "plot06_SoilPH"
    }
}
